equanpy/main.py
equanpy/utils.py
equanpy-1.0.0.dist-info/entry_points.txt
equanpy-1.0.0.dist-info/WHEEL
equanpy-1.0.0.dist-info/METADATA
equanpy-1.0.0.dist-info/RECORD
