Metadata-Version: 2.1
Name: equanpy
Version: 1.0.0
Summary: Python packaging data school
License: MIT
Author: Didier SCHMITT
Author-email: dschmitt@equancy.com
Requires-Python: >=3.8,<4.0
Classifier: License :: OSI Approved :: MIT License
Classifier: Programming Language :: Python :: 3
Classifier: Programming Language :: Python :: 3.10
Classifier: Programming Language :: Python :: 3.8
Classifier: Programming Language :: Python :: 3.9
Requires-Dist: click (>=8.0.3,<9.0.0)
